README.md
setup.cfg
setup.py
GreenHouseEI.egg-info/PKG-INFO
GreenHouseEI.egg-info/SOURCES.txt
GreenHouseEI.egg-info/dependency_links.txt
GreenHouseEI.egg-info/top_level.txt
GreenHouseEI.egg-info/zip-safe
greenhouseEI/__init__.py
greenhouseEI/tools.py