Metadata-Version: 2.1
Name: GreenHouseEI
Version: 0.6
Summary: unzip compressed files that contain plant images, and covert the images into numpy arrays
Home-page: https://github.com/cseseniordesign/plant-phenotyping/tree/master/greenhouseEI
Author: Zhenghui Su, Yifeng Yu, Yinchao He, Phillip Nguyen, Collin Cornman
Author-email: zsu@huskers.unl.edu
License: APACHE2.0
Platform: UNKNOWN
